requests_cache_mongodb
