Metadata-Version: 1.0
Name: requests-cache-mongodb
Version: 0.0.5
Summary: requests session cache with mongodb backend
Home-page: UNKNOWN
Author: linziyan
Author-email: aohan237@gmail.com
License: MIT License
Keywords: requests,cache
Platform: any
